flecsi_sandbox/__init__.py
flecsi_sandbox/__main__.py
flecsi_sandbox/_auxiliary_files/.clang-format
flecsi_sandbox/_auxiliary_files/.gitignore
flecsi_sandbox/_auxiliary_files/README.md
flecsi_sandbox/_auxiliary_files/support/env.yaml
flecsi_sandbox/_internal/fileutils.py
flecsi_sandbox/_internal/main.py
flecsi_sandbox/_internal/options.py
flecsi_sandbox/_internal/templates.py
flecsi_sandbox-0.1.8.dist-info/METADATA
flecsi_sandbox-0.1.8.dist-info/WHEEL
flecsi_sandbox-0.1.8.dist-info/entry_points.txt
flecsi_sandbox-0.1.8.dist-info/top_level.txt
flecsi_sandbox-0.1.8.dist-info/RECORD
